gallavant/__init__.py
gallavant/_frontend.py
gallavant/_version.py
gallavant/gallavant.py
gallavant/labextension/package.json
gallavant/labextension/static/568.534eb8a18bd1a8635b22.js
gallavant/labextension/static/568.a71d833cfd219aef708f.js
gallavant/labextension/static/remoteEntry.6822e34c46bae5faed76.js
gallavant/labextension/static/remoteEntry.d30b6828bbac626cbd4c.js
gallavant/labextension/static/style.js
gallavant/labextension/static/third-party-licenses.json
gallavant/nbextension/extension.js
gallavant/nbextension/index.js
gallavant/nbextension/index.js.LICENSE.txt
gallavant/nbextension/index.js.map
gallavant-0.2.1.data/data/etc/jupyter/nbconfig/notebook.d/gallavant.json
gallavant-0.2.1.data/data/share/jupyter/labextensions/gallavant/install.json
gallavant-0.2.1.data/data/share/jupyter/labextensions/gallavant/package.json
gallavant-0.2.1.data/data/share/jupyter/labextensions/gallavant/static/568.534eb8a18bd1a8635b22.js
gallavant-0.2.1.data/data/share/jupyter/labextensions/gallavant/static/remoteEntry.d30b6828bbac626cbd4c.js
gallavant-0.2.1.data/data/share/jupyter/labextensions/gallavant/static/style.js
gallavant-0.2.1.data/data/share/jupyter/labextensions/gallavant/static/third-party-licenses.json
gallavant-0.2.1.data/data/share/jupyter/nbextensions/gallavant/extension.js
gallavant-0.2.1.data/data/share/jupyter/nbextensions/gallavant/index.js
gallavant-0.2.1.data/data/share/jupyter/nbextensions/gallavant/index.js.LICENSE.txt
gallavant-0.2.1.data/data/share/jupyter/nbextensions/gallavant/index.js.map
gallavant-0.2.1.dist-info/LICENSE.txt
gallavant-0.2.1.dist-info/METADATA
gallavant-0.2.1.dist-info/WHEEL
gallavant-0.2.1.dist-info/top_level.txt
gallavant-0.2.1.dist-info/RECORD
